theatre_au/__init__.py
theatre_au/au.py
theatre_au-0.1a3.dist-info/METADATA
theatre_au-0.1a3.dist-info/WHEEL
theatre_au-0.1a3.dist-info/top_level.txt
theatre_au-0.1a3.dist-info/RECORD
