Metadata-Version: 2.1
Name: theatre-au
Version: 0.1a3
Summary: A very simple time simulation framework, intended for use with actor_au.
Home-page: http://probablytom.com/
Author: Tom Wallis
Author-email: w.wallis.1@research.gla.ac.uk
License: MIT
Platform: UNKNOWN
Classifier: License :: OSI Approved :: MIT License
Classifier: Programming Language :: Python
Classifier: Programming Language :: Python :: 2
Classifier: Programming Language :: Python :: 2.7
Classifier: Programming Language :: Python :: Implementation :: CPython
Classifier: Programming Language :: Python :: Implementation :: PyPy
Requires-Python: <3
